paddleocr_mcp/__init__.py
paddleocr_mcp/__main__.py
paddleocr_mcp/pipelines.py
paddleocr_mcp/py.typed
mseep_paddleocr_mcp-0.2.2.dist-info/METADATA
mseep_paddleocr_mcp-0.2.2.dist-info/WHEEL
mseep_paddleocr_mcp-0.2.2.dist-info/entry_points.txt
mseep_paddleocr_mcp-0.2.2.dist-info/top_level.txt
mseep_paddleocr_mcp-0.2.2.dist-info/RECORD
