Metadata-Version: 2.4
Name: mseep-paddleocr_mcp
Version: 0.2.2
Author-email: mseep <support@skydeck.ai>
Requires-Python: >=3.10
Requires-Dist: mcp>=1.5.0
Requires-Dist: fastmcp>=2.0.0
Requires-Dist: httpx>=0.24.0
Requires-Dist: numpy>=1.24.0
Requires-Dist: pillow>=9.0.0
Requires-Dist: puremagic>=1.30.0
Requires-Dist: typing-extensions>=4.0.0
